CHANGELOG.md
MANIFEST.in
README.rst
setup.cfg
setup.py
detox_bridge/__init__.py
detox_bridge/bridge.js
detox_bridge/detox_bridge.py
detox_bridge/js.py
detox_bridge/node.py
detox_bridge.egg-info/PKG-INFO
detox_bridge.egg-info/SOURCES.txt
detox_bridge.egg-info/dependency_links.txt
detox_bridge.egg-info/not-zip-safe
detox_bridge.egg-info/top_level.txt
docs/Makefile
docs/conf.py
docs/index.rst
docs/installation.rst
docs/make.bat
docs/usage.rst