Metadata-Version: 1.1
Name: detox-bridge
Version: 1.0.2
Summary: A python bridge to the detox greybox testing library
Home-page: https://github.com/kpn-digital/py-detox-bridge
Author: Jan-Eric Duden
Author-email: jan-eric.duden@kpn.com
License: UNKNOWN
Platform: UNKNOWN
Classifier: Development Status :: 5 - Production/Stable
Classifier: Environment :: Web Environment
Classifier: Intended Audience :: Developers
Classifier: Operating System :: OS Independent
Classifier: Programming Language :: Python
Classifier: Programming Language :: Python :: 3
Classifier: Programming Language :: Python :: 3.5
Classifier: Programming Language :: Python :: 3.6
Classifier: Topic :: Internet :: WWW/HTTP
